pegl/__init__.py
pegl/_caching.py
pegl/attribs.py
pegl/config.py
pegl/context.py
pegl/display.py
pegl/enums.py
pegl/errors.py
pegl/image.py
pegl/surface.py
pegl/sync.py
pegl/egl/__init__.py
pegl/egl/_common.py
pegl/egl/egl1_0.py
pegl/egl/egl1_1.py
pegl/egl/egl1_2.py
pegl/egl/egl1_3.py
pegl/egl/egl1_4.py
pegl/egl/egl1_5.py
pegl/ext/__init__.py
Pegl-0.2a1.dist-info/COPYING
Pegl-0.2a1.dist-info/METADATA
Pegl-0.2a1.dist-info/WHEEL
Pegl-0.2a1.dist-info/top_level.txt
Pegl-0.2a1.dist-info/RECORD
