Metadata-Version: 2.1
Name: Pegl
Version: 0.2a1
Summary: Python 3 wrapper for the EGL API
Home-page: https://github.com/perey/pegl
Author: Tim Pederick
Classifier: Development Status :: 3 - Alpha
Classifier: Intended Audience :: Developers
Classifier: License :: OSI Approved :: GNU General Public License v3 or later (GPLv3+)
Classifier: Operating System :: OS Independent
Classifier: Programming Language :: Python
Classifier: Programming Language :: Python :: 3
Classifier: Programming Language :: Python :: 3.7
Classifier: Programming Language :: Python :: 3.8
Classifier: Programming Language :: Python :: 3.9
Classifier: Topic :: Multimedia :: Graphics
Classifier: Topic :: Software Development :: Libraries
License-File: COPYING
Requires-Dist: aenum (==2.2.6)
